rust_x3dh-0.1.1.dist-info/METADATA
rust_x3dh-0.1.1.dist-info/WHEEL
rust_x3dh-0.1.1.dist-info/license_files/LICENSE
rust_x3dh.libs/libgcc_s-1e52349c.so.1
rust_x3dh/__init__.py
rust_x3dh/rust_x3dh.abi3.so
rust_x3dh-0.1.1.dist-info/RECORD
