Metadata-Version: 2.1
Name: rust_x3dh
Version: 0.1.1
Classifier: Intended Audience :: Developers
Classifier: License :: OSI Approved :: MIT License
Classifier: Operating System :: MacOS
Classifier: Operating System :: Microsoft :: Windows
Classifier: Operating System :: POSIX :: Linux
Classifier: Programming Language :: Python :: 3.9
Classifier: Programming Language :: Python
Classifier: Programming Language :: Rust
Classifier: Programming Language :: Python :: Implementation :: CPython
Classifier: Programming Language :: Python :: Implementation :: PyPy
License-File: LICENSE
Summary: Embeded the xxxdh, which iplementation of the Extended Triple Diffie-Hellman key exchange protocol written in Rust, on Python. xxxdh is written by Olexander Yermakov.
Keywords: crypto,cryptography,x3dh
Author: Klaus Wong <wch.klaus@gmail.com>
Author-email: Klaus Wong <wch.klaus@gmail.com>
License: MIT
Requires-Python: >=3.9
Project-URL: Homepage, https://github.com/hkk97/rust_x3dh
